bekapoxd.py
bekapoxd-1.0.0.dist-info/WHEEL
bekapoxd-1.0.0.dist-info/METADATA
bekapoxd-1.0.0.dist-info/RECORD
